{
  "id": "guilin_museum",
  "name": "桂林博物馆",
  "englishName": "Guilin Museum",
  "city": "桂林",
  "province": "广西",
  "category": "综合",
  "founded": 1963,
  "area": null,
  "annualVisitors": null,
  "freeEntry": false,
  "address": "广西桂林（坐标定位，详细地址请查看官网）",
  "website": "http://www.guilinmuseum.org.cn/",
  "phone": "0773-5800849",
  "openingHours": "请查看官网",
  "summary": "桂林博物馆位于广西桂林，是一座以地方文化、历史记忆与综合收藏为主要内容的综合类博物馆。馆内展陈通常围绕常设收藏、专题展览与公共教育展开，适合作为了解当地文化脉络的参观点。",
  "highlights": [
    "综合历史陈列",
    "馆藏文物精品",
    "公共教育活动"
  ],
  "images": [],
  "latitude": 25.24817,
  "longitude": 110.16065,
  "grade": null
}