{
  "id": "pingyao_museum",
  "name": "平遥古城博物馆",
  "englishName": "Pingyao Ancient City Museum",
  "city": "晋中",
  "province": "山西",
  "category": "历史",
  "founded": 1986,
  "area": null,
  "annualVisitors": null,
  "freeEntry": false,
  "address": "山西省晋中市平遥县政府街100号",
  "website": "http://www.pymuseum.com/",
  "phone": "0354-5620146",
  "openingHours": "请查看官网",
  "summary": "平遥古城博物馆位于世界文化遗产平遥古城内，展示明清两代晋商文化、票号金融历史及平遥传统民居生活，是了解中国古代金融文明的重要窗口。",
  "highlights": [
    "晋商票号历史",
    "明清金融文物",
    "古城民居建筑群"
  ],
  "images": [],
  "latitude": 37.1895,
  "longitude": 112.1762,
  "grade": "国家一级博物馆"
}